clamd/__init__.py
clamd-1.0.2.dist-info/zip-safe
clamd-1.0.2.dist-info/metadata.json
clamd-1.0.2.dist-info/RECORD
clamd-1.0.2.dist-info/top_level.txt
clamd-1.0.2.dist-info/DESCRIPTION.rst
clamd-1.0.2.dist-info/METADATA
clamd-1.0.2.dist-info/WHEEL
