Metadata-Version: 1.1
Name: clamd
Version: 1.0.2
Summary: Clamd is a python interface to Clamd (Clamav daemon).
Home-page: https://github.com/graingert/python-clamd
Author: Thomas Grainger
Author-email: python-clamd@graingert.co.uk
License: UNKNOWN
Keywords: python,clamav,antivirus,scanner,virus,libclamav,clamd
Platform: UNKNOWN
Classifier: License :: OSI Approved :: GNU Library or Lesser General Public License (LGPL)
